emrt.necd.content-2.6.3-py2.7-nspkg.pth
emrt/necd/content/INTEGRATION.txt
emrt/necd/content/__init__.py
emrt/necd/content/__init__.pyc
emrt/necd/content/comment.py
emrt/necd/content/comment.pyc
emrt/necd/content/commentanswer.py
emrt/necd/content/commentanswer.pyc
emrt/necd/content/commentextender.py
emrt/necd/content/commentextender.pyc
emrt/necd/content/conclusions.py
emrt/necd/content/conclusions.pyc
emrt/necd/content/configure.zcml
emrt/necd/content/constants.py
emrt/necd/content/constants.pyc
emrt/necd/content/converter.py
emrt/necd/content/converter.pyc
emrt/necd/content/crons.py
emrt/necd/content/crons.pyc
emrt/necd/content/inbox_sections.py
emrt/necd/content/inbox_sections.pyc
emrt/necd/content/indexers.py
emrt/necd/content/indexers.pyc
emrt/necd/content/necdfile.py
emrt/necd/content/necdfile.pyc
emrt/necd/content/nfr_code_matching.py
emrt/necd/content/nfr_code_matching.pyc
emrt/necd/content/observation.py
emrt/necd/content/observation.pyc
emrt/necd/content/overrides.zcml
emrt/necd/content/patches.py
emrt/necd/content/patches.pyc
emrt/necd/content/patches.zcml
emrt/necd/content/permissions.zcml
emrt/necd/content/profiles.zcml
emrt/necd/content/question.py
emrt/necd/content/question.pyc
emrt/necd/content/reviewfolder.py
emrt/necd/content/reviewfolder.pyc
emrt/necd/content/setuphandlers.py
emrt/necd/content/setuphandlers.pyc
emrt/necd/content/subscribers.py
emrt/necd/content/subscribers.pyc
emrt/necd/content/subscriptionconfiguration.py
emrt/necd/content/subscriptionconfiguration.pyc
emrt/necd/content/tests.py
emrt/necd/content/tests.pyc
emrt/necd/content/timeit.py
emrt/necd/content/timeit.pyc
emrt/necd/content/transform_html_to_docx.py
emrt/necd/content/utils.py
emrt/necd/content/utils.pyc
emrt/necd/content/views.zcml
emrt/necd/content/vocabularies.py
emrt/necd/content/vocabularies.pyc
emrt/necd/content/vocabularies.zcml
emrt/necd/content/adapters/__init__.py
emrt/necd/content/adapters/__init__.pyc
emrt/necd/content/adapters/configure.zcml
emrt.necd.content-2.6.3.dist-info/METADATA
emrt.necd.content-2.6.3.dist-info/WHEEL
emrt.necd.content-2.6.3.dist-info/entry_points.txt
emrt.necd.content-2.6.3.dist-info/namespace_packages.txt
emrt.necd.content-2.6.3.dist-info/top_level.txt
emrt.necd.content-2.6.3.dist-info/RECORD
