Metadata-Version: 2.1
Name: emrt.necd.content
Version: 2.6.3
Summary: Content-types for EMRT-NECD Review Tool
Home-page: https://github.com/eea/emrt.necd.content/
Author: Mikel Larreategi
Author-email: mlarreategi@codesyntax.com
License: GPL
Platform: UNKNOWN
Classifier: Framework :: Plone
Classifier: Programming Language :: Python
Classifier: Topic :: Software Development :: Libraries :: Python Modules
Requires-Dist: setuptools
Requires-Dist: futures
Requires-Dist: plone.app.dexterity[relations]
Requires-Dist: plone.namedfile[blobs]
Requires-Dist: collective.z3cform.datagridfield
Requires-Dist: plone.formwidget.multifile
Requires-Dist: plone.api
Requires-Dist: Products.ATVocabularyManager
Requires-Dist: plone.app.versioningbehavior
Requires-Dist: plone.app.workflowmanager
Requires-Dist: plone.app.ldap
Requires-Dist: cs.htmlmailer
Requires-Dist: collective.deletepermission
Requires-Dist: tablib
Requires-Dist: python-docx (==0.8.5)
Requires-Dist: zc.dict
Requires-Dist: collective.monkeypatcher
Requires-Dist: openpyxl
Requires-Dist: five.pt
Requires-Dist: simplejson
Requires-Dist: beautifulsoup4
Requires-Dist: requests
Requires-Dist: html2text
Requires-Dist: collective.exportimport
